tytr/__init__.py
tytr/_internal.py
tytr/_version.py
tytr/cli.py
tytr/core.py
tytr/py.typed
tytr/testing.py
tytr/utilities.py
tytr-0.1.1.dist-info/METADATA
tytr-0.1.1.dist-info/WHEEL
tytr-0.1.1.dist-info/entry_points.txt
tytr-0.1.1.dist-info/licenses/LICENSE
tytr-0.1.1.dist-info/RECORD
